isla/__init__.py
isla/__main__.py
isla/cli.py
isla/derivation_tree.py
isla/evaluator.py
isla/existential_helpers.py
isla/fuzzer.py
isla/global_config.py
isla/helpers.py
isla/isla_predicates.py
isla/isla_shortcuts.py
isla/language.py
isla/mutator.py
isla/optimizer.py
isla/parser.py
isla/performance_evaluator.py
isla/solver.py
isla/three_valued_truth.py
isla/trie.py
isla/type_defs.py
isla/z3_helpers.py
isla/bnf/__init__.py
isla/bnf/bnfLexer.py
isla/bnf/bnfListener.py
isla/bnf/bnfParser.py
isla/isla_language/IslaLanguageLexer.py
isla/isla_language/IslaLanguageListener.py
isla/isla_language/IslaLanguageParser.py
isla/isla_language/__init__.py
isla/mexpr_lexer/MexprLexer.py
isla/mexpr_lexer/__init__.py
isla/mexpr_parser/MexprParser.py
isla/mexpr_parser/MexprParserListener.py
isla/mexpr_parser/__init__.py
isla/resources/.islarc
isla/resources/cli_stubs/README.md
isla/resources/cli_stubs/constraint.isla
isla/resources/cli_stubs/grammar.bnf
isla/resources/cli_stubs/grammar.py
isla_formalizations/__init__.py
isla_formalizations/csv.py
isla_formalizations/rest.py
isla_formalizations/scriptsizec.py
isla_formalizations/simple_tar.py
isla_formalizations/tar.py
isla_formalizations/xml_lang.py
isla_solver-1.14.4.dist-info/COPYING
isla_solver-1.14.4.dist-info/METADATA
isla_solver-1.14.4.dist-info/WHEEL
isla_solver-1.14.4.dist-info/entry_points.txt
isla_solver-1.14.4.dist-info/top_level.txt
isla_solver-1.14.4.dist-info/RECORD
