Metadata-Version: 2.1
Name: isla-solver
Version: 1.14.4
Summary: The ISLa Input Specification Language and its solver.
Author-email: Dominic Steinhoefel <dominic.steinhoefel@cispa.de>
License: GNU GENERAL PUBLIC LICENSE
Project-URL: Homepage, https://github.com/rindPHI/isla/
Project-URL: Bug Tracker, https://github.com/rindPHI/isla/issues
Classifier: Intended Audience :: Science/Research
Classifier: License :: OSI Approved :: GNU General Public License v3 (GPLv3)
Classifier: Programming Language :: Python :: 3.10
Classifier: Operating System :: OS Independent
Classifier: Topic :: Scientific/Engineering
Classifier: Topic :: Security
Classifier: Topic :: Software Development :: Testing
Requires-Python: >=3.10
License-File: COPYING
Requires-Dist: antlr4-python3-runtime >=4.13
Requires-Dist: datrie >=0.8.2
Requires-Dist: grammar-to-regex >=0.0.4
Requires-Dist: grammar-graph >=0.1.15
Requires-Dist: ijson >=3.1.4
Requires-Dist: packaging >=21.3
Requires-Dist: pathos >=0.2.9
Requires-Dist: proxyorderedset >=0.3.5
Requires-Dist: returns >=0.21.0
Requires-Dist: toml >=0.10.2
Requires-Dist: wheel >=0.37.1
Requires-Dist: z3-solver <=4.11.2.0,>=4.8.17.0
Provides-Extra: dev
Requires-Dist: black >=22.8.0 ; extra == 'dev'
Requires-Dist: build >=0.8.0 ; extra == 'dev'
Requires-Dist: flake8 >=5.0.4 ; extra == 'dev'
Requires-Dist: setuptools-antlr >=0.4.0 ; extra == 'dev'
Requires-Dist: sphinx >=6.1.3 ; extra == 'dev'
Requires-Dist: sphinx-book-theme >=1.0.0 ; extra == 'dev'
Requires-Dist: twine >=4.0.1 ; extra == 'dev'
Provides-Extra: test
Requires-Dist: docutils >=0.18.1 ; extra == 'test'
Requires-Dist: matplotlib >=3.5.3 ; extra == 'test'
Requires-Dist: pytest-cov >=3.0.0 ; extra == 'test'
Requires-Dist: pytest-html >=3.1.1 ; extra == 'test'
Requires-Dist: pytest-profiling >=1.7.0 ; extra == 'test'
Requires-Dist: pytest-pycharm >=0.7.0 ; extra == 'test'
Requires-Dist: pytest-randomly >=3.12.0 ; extra == 'test'
Requires-Dist: pytest-rerunfailures >=10.2 ; extra == 'test'
Requires-Dist: pytest-xdist >=2.4.0 ; extra == 'test'
Requires-Dist: pytest >=7.1.2 ; extra == 'test'
Requires-Dist: tox >=3.25.0 ; extra == 'test'
